setup.cfg
setup.py
consul_contents/__init__.py
consul_contents/consul.py
consul_contents.egg-info/PKG-INFO
consul_contents.egg-info/SOURCES.txt
consul_contents.egg-info/dependency_links.txt
consul_contents.egg-info/not-zip-safe
consul_contents.egg-info/requires.txt
consul_contents.egg-info/top_level.txt