Metadata-Version: 1.0
Name: consul-contents
Version: 1.0.0
Summary: This is for loading key-value stored on consul server
Home-page: https://github.com/vidur-88/consul_contents.git
Author: vikash gupta
Author-email: vgupta840@gmail.com
License: UNKNOWN
Platform: UNKNOWN
